Metadata-Version: 1.1
Name: hellobomma
Version: 1.0.4
Summary: An basic hello world program
Home-page: https://github.com/bomma-anil/hello-world.git
Author: bomma.anil
Author-email: bomma.anil@stackaero.com
License: MIT
Keywords: hello function
Platform: UNKNOWN
Classifier: Development Status :: 4 - Beta
Classifier: Intended Audience :: Developers
Classifier: Topic :: Internet
Classifier: License :: OSI Approved :: MIT License
Classifier: Programming Language :: Python
Classifier: Programming Language :: Python :: 2
Classifier: Programming Language :: Python :: 2.6
Classifier: Programming Language :: Python :: 2.7
Classifier: Programming Language :: Python :: 3
Classifier: Programming Language :: Python :: 3.3
Classifier: Programming Language :: Python :: 3.4
Classifier: Programming Language :: Python :: 3.5
